tryalgo/PC_tree.py
tryalgo/Sequence.py
tryalgo/__init__.py
tryalgo/a_star.py
tryalgo/anagrams.py
tryalgo/arithm.py
tryalgo/arithm_expr_eval.py
tryalgo/arithm_expr_target.py
tryalgo/bellman_ford.py
tryalgo/bfs.py
tryalgo/biconnected_components.py
tryalgo/binary_search.py
tryalgo/bipartite_matching.py
tryalgo/bipartite_vertex_cover.py
tryalgo/closest_points.py
tryalgo/closest_values.py
tryalgo/convex_hull.py
tryalgo/dancing_links.py
tryalgo/dfs.py
tryalgo/dijkstra.py
tryalgo/dilworth.py
tryalgo/dinic.py
tryalgo/dist_grid.py
tryalgo/dyn_prog_tricks.py
tryalgo/edmonds_karp.py
tryalgo/eulerian_tour.py
tryalgo/fast_exponentiation.py
tryalgo/fenwick.py
tryalgo/fft.py
tryalgo/floyd_warshall.py
tryalgo/ford_fulkerson.py
tryalgo/freivalds.py
tryalgo/gale_shapley.py
tryalgo/gauss_jordan.py
tryalgo/graph.py
tryalgo/graph01.py
tryalgo/hamiltonian_cycle.py
tryalgo/horn_sat.py
tryalgo/huffman.py
tryalgo/interval_cover.py
tryalgo/interval_tree.py
tryalgo/intervals_union.py
tryalgo/karatsuba.py
tryalgo/knapsack.py
tryalgo/knuth_morris_pratt.py
tryalgo/kruskal.py
tryalgo/kuhn_munkres.py
tryalgo/kuhn_munkres_n4.py
tryalgo/laser_mirrors.py
tryalgo/left_right_inversions.py
tryalgo/levenshtein.py
tryalgo/longest_common_subsequence.py
tryalgo/longest_increasing_subsequence.py
tryalgo/lowest_common_ancestor.py
tryalgo/majority.py
tryalgo/manacher.py
tryalgo/matrix_chain_mult.py
tryalgo/max_interval_intersec.py
tryalgo/merge_ordered_lists.py
tryalgo/min_mean_cycle.py
tryalgo/next_permutation.py
tryalgo/our_heap.py
tryalgo/our_queue.py
tryalgo/our_std.py
tryalgo/pareto.py
tryalgo/partition_refinement.py
tryalgo/permutation_rank.py
tryalgo/polygon.py
tryalgo/predictive_text.py
tryalgo/primes.py
tryalgo/rabin_karp.py
tryalgo/range_minimum_query.py
tryalgo/rectangles_from_grid.py
tryalgo/rectangles_from_histogram.py
tryalgo/rectangles_from_points.py
tryalgo/roman_numbers.py
tryalgo/scalar.py
tryalgo/shortest_cycle.py
tryalgo/skip_list.py
tryalgo/strongly_connected_components.py
tryalgo-1.7.0.dist-info/LICENSE
tryalgo-1.7.0.dist-info/METADATA
tryalgo-1.7.0.dist-info/WHEEL
tryalgo-1.7.0.dist-info/top_level.txt
tryalgo-1.7.0.dist-info/RECORD
