Metadata-Version: 2.1
Name: tryalgo
Version: 1.7.0
Summary: Algorithms and data structures for preparing programming competitions
Home-page: https://jilljenn.github.io/tryalgo/
Author: Jill-Jênn Vie and Christoph Dürr
Author-email: christoph.durr@lip6.fr
License: MIT
Keywords: algorithms data-structures programming competition
Classifier: Development Status :: 5 - Production/Stable
Classifier: Intended Audience :: Developers
Classifier: Topic :: Software Development :: Build Tools
Classifier: License :: OSI Approved :: MIT License
Classifier: Programming Language :: Python :: 3
License-File: LICENSE
